d2lparser/__init__.py
d2lparser/crc.py
d2lparser/d2lheader.py
d2lparser/d2lparser.py
d2lparser/encryption.py
d2lparser/exceptions.py
d2lparser/packet.py
d2lparser-0.2.4.dist-info/LICENSE
d2lparser-0.2.4.dist-info/METADATA
d2lparser-0.2.4.dist-info/WHEEL
d2lparser-0.2.4.dist-info/top_level.txt
d2lparser-0.2.4.dist-info/RECORD
