Metadata-Version: 2.1
Name: d2lparser
Version: 0.2.4
Summary: A parser for D2L data packets
Home-page: https://gitlab.com/rescoopvpp/d2lparser
Author: Evert Borghgraef
License: MIT
Project-URL: Docs, https://gitlab.com/rescoopvpp/d2lparser/README.md
Project-URL: Bugs, https://gitlab.com/rescoopvpp/d2lparser/-/issues
Platform: any
Classifier: Programming Language :: Python :: 3
Classifier: License :: OSI Approved :: MIT License
Classifier: Operating System :: OS Independent
Requires-Python: >=3.6
License-File: LICENSE
Requires-Dist: bitstring (==3.1.9)
Requires-Dist: pycryptodome (==3.14.1)
